orgapp/__init__.py
orgapp/__main__.py
orgapp/logos.py
orgapp/main.py
orgapp/address_book/README.md
orgapp/address_book/__init__.py
orgapp/address_book/__main__.py
orgapp/address_book/address_book.py
orgapp/address_book/classes_ab.py
orgapp/bandergoose/1-1.png
orgapp/bandergoose/1-2.png
orgapp/bandergoose/1-3.png
orgapp/bandergoose/1-4.png
orgapp/bandergoose/1-5.png
orgapp/bandergoose/__init__.py
orgapp/bandergoose/__main__.py
orgapp/bandergoose/background.png
orgapp/bandergoose/bandergoose.py
orgapp/bandergoose/bonus.png
orgapp/bandergoose/enemy.png
orgapp/bandergoose/explosion.png
orgapp/bandergoose/player.png
orgapp/hannoitower/__init__.py
orgapp/hannoitower/__main__.py
orgapp/hannoitower/hannoitower.py
orgapp/note_book/README.md
orgapp/note_book/__init__.py
orgapp/note_book/__main__.py
orgapp/note_book/classes_nb.py
orgapp/note_book/note_book.py
orgapp/snake/__init__.py
orgapp/snake/__main__.py
orgapp/snake/snake.py
orgapp/sorter/README.md
orgapp/sorter/__init__.py
orgapp/sorter/__main__.py
orgapp/sorter/sorter.py
orgapp/tictactoe/__init__.py
orgapp/tictactoe/__main__.py
orgapp/tictactoe/tictactoe.py
orgApp-0.0.3.dist-info/LICENSE
orgApp-0.0.3.dist-info/METADATA
orgApp-0.0.3.dist-info/WHEEL
orgApp-0.0.3.dist-info/entry_points.txt
orgApp-0.0.3.dist-info/top_level.txt
orgApp-0.0.3.dist-info/RECORD
