Metadata-Version: 2.1
Name: orgApp
Version: 0.0.3
Summary: personal organizing tool
Home-page: https://github.com/Vskesha/orgApp
Author: Vasyl Boliukh, Olga Sirenko, Oleh Kolobaiev, Andriy Batig
Author-email: vskesha@gmail.com, olga19022020@gmail.com, o.kolobaiev@gmail.com, ashabatig1992@gmail.com
License: MIT License
License-File: LICENSE
Requires-Dist: markdown
Requires-Dist: colorama ==0.4.6
Requires-Dist: prompt-toolkit ==3.0.39
Requires-Dist: pygame ==2.5.1
Requires-Dist: wcwidth ==0.2.6
Requires-Dist: Faker ==19.6.1
